tinyagent_deepsearch/__init__.py
tinyagent_deepsearch/core.py
tinyagent_deepsearch/exceptions.py
tinyagent_deepsearch-0.1.3.dist-info/licenses/LICENSE
tinyagent_deepsearch-0.1.3.dist-info/METADATA
tinyagent_deepsearch-0.1.3.dist-info/WHEEL
tinyagent_deepsearch-0.1.3.dist-info/top_level.txt
tinyagent_deepsearch-0.1.3.dist-info/RECORD
