Metadata-Version: 2.4
Name: tinyagent_deepsearch
Version: 0.1.3
Summary: A Python library for performing deep research using AI agents and Firecrawl, with support for custom models and report generation.
Author-email: larock22 <your_email@example.com>
License-Expression: MIT
Project-URL: Homepage, https://github.com/alchemiststudiosDOTai/tinyagent_deepsearch
Project-URL: Repository, https://github.com/alchemiststudiosDOTai/tinyagent_deepsearch
Classifier: Programming Language :: Python :: 3
Classifier: Operating System :: OS Independent
Classifier: Intended Audience :: Developers
Classifier: Topic :: Scientific/Engineering :: Artificial Intelligence
Classifier: Topic :: Internet :: WWW/HTTP :: Indexing/Search
Requires-Python: >=3.8
License-File: LICENSE
Requires-Dist: python-dotenv>=0.20.0
Requires-Dist: pydantic>=2.0.0
Requires-Dist: openai>=1.0.0
Requires-Dist: tenacity>=8.0.0
Requires-Dist: firecrawl-py>=0.0.14
Requires-Dist: tiny_agent_os
Dynamic: license-file
